LICENSE
py_helium_console_client/__init__.py
py_helium_console_client/api_calls.py
py_helium_console_client/client.py
py_helium_console_client/exceptions.py
py_helium_console_client/models.py
py_helium_console_client-0.1.2.dist-info/LICENSE
py_helium_console_client-0.1.2.dist-info/WHEEL
py_helium_console_client-0.1.2.dist-info/METADATA
py_helium_console_client-0.1.2.dist-info/RECORD
