Metadata-Version: 2.1
Name: py-helium-console-client
Version: 0.1.2
Summary: An unofficial Python Client library for the Helium Console API.
Home-page: https://github.com/evandiewald/py-helium-console-client
License: MIT
Keywords: helium,console
Author: Evan Diewald
Author-email: evandiewald@gmail.com
Requires-Python: >=3.7,<4.0
Classifier: License :: OSI Approved :: MIT License
Classifier: Programming Language :: Python :: 3
Classifier: Programming Language :: Python :: 3.10
Classifier: Programming Language :: Python :: 3.7
Classifier: Programming Language :: Python :: 3.8
Classifier: Programming Language :: Python :: 3.9
Requires-Dist: certifi (>=2021.10.8,<2022.0.0)
Requires-Dist: idna (>=3.3,<4.0)
Requires-Dist: pydantic (>=1.8.2,<2.0.0)
Requires-Dist: requests (>=2.26.0,<3.0.0)
Project-URL: Repository, https://github.com/evandiewald/py-helium-console-client
